{"dates":[],"derivedDimensions":[],"derivedMeasures":[{"conditionalFormatting":{},"field":"PoP_Percent_Change","format":{"customFormat":"[\"▲#,###.##%;▼-#,###.##%;0\",100]","delimiters":{}},"label":"PoP_Percent_Change","showInExplorer":true}],"dimensions":[{"conditionalFormatting":{},"customActions":[],"field":"RetailStore_Name","linkTemplateEnabled":true,"members":[],"recordDisplayFields":["RetailStore_Name"],"recordIdField":"AF_ID","salesforceActions":[],"salesforceActionsEnabled":true}],"measures":[],"organizations":[],"showDetailsDefaultFields":[]}