{"fileFormat":{"charsetName":"UTF-8","fieldsDelimitedBy":",","fieldsEnclosedBy":"\"","linesTerminatedBy":"\n"},"objects":[{"connector":"CSV","fullyQualifiedName":"Team_Performance3_csv","label":"Team_Performance3.csv","name":"Team_Performance3_csv","fields":[{"fullyQualifiedName":"EmployeeSatisfaction","name":"EmployeeSatisfaction","type":"Text","label":"EmployeeSatisfaction"},{"fullyQualifiedName":"SmallPhotoUrl","name":"SmallPhotoUrl","type":"Text","label":"SmallPhotoUrl"},{"fullyQualifiedName":"EmployeeType","name":"EmployeeType","type":"Text","label":"EmployeeType"},{"fullyQualifiedName":"Name","name":"Name","type":"Text","label":"Name"},{"fullyQualifiedName":"AgentCommunication","name":"AgentCommunication","type":"Text","label":"AgentCommunication"},{"fullyQualifiedName":"WaitTime","name":"WaitTime","type":"Text","label":"WaitTime"},{"fullyQualifiedName":"AgentExperience","name":"AgentExperience","type":"Text","label":"AgentExperience"},{"fullyQualifiedName":"Order","name":"Order","type":"Numeric","label":"Order","precision":18,"defaultValue":"0","scale":0,"format":"0"},{"fullyQualifiedName":"HandledWithinSLA","name":"HandledWithinSLA","type":"Numeric","label":"HandledWithinSLA","precision":18,"defaultValue":"0","scale":0,"format":"0"},{"fullyQualifiedName":"VsLastQuarter","name":"VsLastQuarter","type":"Numeric","label":"VsLastQuarter","precision":18,"defaultValue":"0","scale":0,"format":"0"},{"fullyQualifiedName":"NPS","name":"NPS","type":"Numeric","label":"NPS","precision":18,"defaultValue":"0","scale":0,"format":"0"},{"fullyQualifiedName":"PredictedNPS","name":"PredictedNPS","type":"Numeric","label":"PredictedNPS","precision":18,"defaultValue":"0","scale":0,"format":"0"},{"fullyQualifiedName":"NroOfClaimsHandled","name":"NroOfClaimsHandled","type":"Numeric","label":"NroOfClaimsHandled","precision":18,"defaultValue":"0","scale":0,"format":"0"}]}]}