{"fileFormat":{"charsetName":"UTF-8","fieldsDelimitedBy":",","fieldsEnclosedBy":"\"","linesTerminatedBy":"\n"},"objects":[{"connector":"CSV","fullyQualifiedName":"ServiceActivity_csv","label":"ServiceActivity.csv","name":"ServiceActivity_csv","fields":[{"fullyQualifiedName":"LastModifiedDate","name":"LastModifiedDate","type":"Date","label":"LastModifiedDate","format":"yyyy-MM-dd'T'HH:mm:ss.SSS'Z'"},{"fullyQualifiedName":"Case_RecordType_Name","name":"Case_RecordType_Name","type":"Text","label":"Case.RecordType.Name"},{"fullyQualifiedName":"WhatId","name":"WhatId","type":"Text","label":"WhatId"},{"fullyQualifiedName":"Case_Role_Name","name":"Case_Role_Name","type":"Text","label":"Case.Role.Name"},{"fullyQualifiedName":"Case_CreatedDate","name":"Case_CreatedDate","type":"Date","label":"Case.CreatedDate","format":"yyyy-MM-dd'T'HH:mm:ss.SSS'Z'"},{"fullyQualifiedName":"CallDisposition","name":"CallDisposition","type":"Text","label":"CallDisposition"},{"fullyQualifiedName":"CallType","name":"CallType","type":"Text","label":"CallType"},{"fullyQualifiedName":"ActivityIsClosed","name":"ActivityIsClosed","type":"Text","label":"ActivityIsClosed"},{"fullyQualifiedName":"Case_Type","name":"Case_Type","type":"Text","label":"Case.Type"},{"fullyQualifiedName":"Case_Type_of_Support__c","name":"Case_Type_of_Support__c","type":"Text","label":"Case.Type_of_Support__c"},{"fullyQualifiedName":"IsClosed","name":"IsClosed","type":"Text","label":"IsClosed"},{"fullyQualifiedName":"Case_Origin","name":"Case_Origin","type":"Text","label":"Case.Origin"},{"fullyQualifiedName":"Case_IsClosed","name":"Case_IsClosed","type":"Text","label":"Case.IsClosed"},{"fullyQualifiedName":"Owner_Id","name":"Owner_Id","type":"Text","label":"Owner.Id"},{"fullyQualifiedName":"Case_CurrentDate","name":"Case_CurrentDate","type":"Date","label":"Case.CurrentDate","format":"yyyy-MM-dd'T'HH:mm:ss.SSS'Z'"},{"fullyQualifiedName":"Case_Reason","name":"Case_Reason","type":"Text","label":"Case.Reason"},{"fullyQualifiedName":"IsCall","name":"IsCall","type":"Text","label":"IsCall"},{"fullyQualifiedName":"Case_Id","name":"Case_Id","type":"Text","label":"Case.Id"},{"fullyQualifiedName":"OwnerId","name":"OwnerId","type":"Text","label":"OwnerId"},{"fullyQualifiedName":"EndDateTime","name":"EndDateTime","type":"Date","label":"EndDateTime","format":"yyyy-MM-dd'T'HH:mm:ss.SSS'Z'"},{"fullyQualifiedName":"Case_ClosedDate","name":"Case_ClosedDate","type":"Date","label":"Case.ClosedDate","format":"yyyy-MM-dd'T'HH:mm:ss.SSS'Z'"},{"fullyQualifiedName":"Owner_UserRoleId","name":"Owner_UserRoleId","type":"Text","label":"Owner.UserRoleId"},{"fullyQualifiedName":"Case_Priority","name":"Case_Priority","type":"Text","label":"Case.Priority"},{"fullyQualifiedName":"Status","name":"Status","type":"Text","label":"Status"},{"fullyQualifiedName":"Case_Account_Name","name":"Case_Account_Name","type":"Text","label":"Case.Account.Name"},{"fullyQualifiedName":"Owner_Name","name":"Owner_Name","type":"Text","label":"Owner.Name"},{"fullyQualifiedName":"ActivityDate","name":"ActivityDate","type":"Date","label":"ActivityDate","format":"yyyy-MM-dd"},{"fullyQualifiedName":"Case_Status","name":"Case_Status","type":"Text","label":"Case.Status"},{"fullyQualifiedName":"Priority","name":"Priority","type":"Text","label":"Priority"},{"fullyQualifiedName":"ActivityType","name":"ActivityType","type":"Text","label":"ActivityType"},{"fullyQualifiedName":"IsActivity","name":"IsActivity","type":"Text","label":"IsActivity"},{"fullyQualifiedName":"Case_Product_Family_KB__c","name":"Case_Product_Family_KB__c","type":"Text","label":"Case.Product_Family_KB__c"},{"fullyQualifiedName":"Subject","name":"Subject","type":"Text","label":"Subject"},{"fullyQualifiedName":"CallObject","name":"CallObject","type":"Text","label":"CallObject"},{"fullyQualifiedName":"Type","name":"Type","type":"Text","label":"Type"},{"fullyQualifiedName":"TaskSubtype","name":"TaskSubtype","type":"Text","label":"TaskSubtype"},{"fullyQualifiedName":"Case_Account_Id","name":"Case_Account_Id","type":"Text","label":"Case.Account.Id"},{"fullyQualifiedName":"Case_CaseNumber","name":"Case_CaseNumber","type":"Text","label":"Case.CaseNumber"},{"fullyQualifiedName":"CreatedDate","name":"CreatedDate","type":"Date","label":"CreatedDate","format":"yyyy-MM-dd'T'HH:mm:ss.SSS'Z'"},{"fullyQualifiedName":"Id","name":"Id","type":"Text","label":"Id"},{"fullyQualifiedName":"EventSubtype","name":"EventSubtype","type":"Text","label":"EventSubtype"},{"fullyQualifiedName":"ShowAs","name":"ShowAs","type":"Text","label":"ShowAs"},{"fullyQualifiedName":"DurationInMinutes","name":"DurationInMinutes","type":"Numeric","label":"DurationInMinutes","precision":18,"defaultValue":"null","scale":0,"format":"0"},{"fullyQualifiedName":"Case_Time_Open__c","name":"Case_Time_Open__c","type":"Numeric","label":"Case.Time_Open__c","precision":18,"defaultValue":"null","scale":0,"format":"0"},{"fullyQualifiedName":"Case_ED_Outcome__c","name":"Case_ED_Outcome__c","type":"Numeric","label":"Case.ED_Outcome__c","precision":18,"defaultValue":"null","scale":1,"format":"0.#","decimalSeparator":"."},{"fullyQualifiedName":"CallDurationInSeconds","name":"CallDurationInSeconds","type":"Numeric","label":"CallDurationInSeconds","precision":18,"defaultValue":"null","scale":0,"format":"0"}]}]}