{"fileFormat":{"charsetName":"UTF-8","fieldsDelimitedBy":",","fieldsEnclosedBy":"\"","linesTerminatedBy":"\n"},"objects":[{"connector":"CSV","fullyQualifiedName":"opportunity13_csv","label":"opportunity13.csv","name":"opportunity13_csv","fields":[{"fullyQualifiedName":"Account_Type","name":"Account_Type","type":"Text","label":"Account_Type"},{"fullyQualifiedName":"AccountId","name":"AccountId","type":"Text","label":"AccountId"},{"fullyQualifiedName":"HasOpportunityLineItem","name":"HasOpportunityLineItem","type":"Text","label":"HasOpportunityLineItem"},{"fullyQualifiedName":"User_Role_ForecastManager_UniqueUserName","name":"User_Role_ForecastManager_UniqueUserName","type":"Text","label":"User_Role_ForecastManager_UniqueUserName"},{"fullyQualifiedName":"Account_User_SmallPhotoUrl","name":"Account_User_SmallPhotoUrl","type":"Text","label":"Account_User_SmallPhotoUrl"},{"fullyQualifiedName":"Account_User_UserRoleId","name":"Account_User_UserRoleId","type":"Text","label":"Account_User_UserRoleId"},{"fullyQualifiedName":"CloseDate","name":"CloseDate","type":"Date","label":"CloseDate","format":"yyyy-MM-dd"},{"fullyQualifiedName":"Name","name":"Name","type":"Text","label":"Name"},{"fullyQualifiedName":"User_Role_ForecastManager_Name","name":"User_Role_ForecastManager_Name","type":"Text","label":"User_Role_ForecastManager_Name"},{"fullyQualifiedName":"User_Username","name":"User_Username","type":"Text","label":"User_Username"},{"fullyQualifiedName":"Account_User_IsActive","name":"Account_User_IsActive","type":"Text","label":"Account_User_IsActive"},{"fullyQualifiedName":"User_Role_Name","name":"User_Role_Name","type":"Text","label":"User_Role_Name"},{"fullyQualifiedName":"User_Role_ForecastManager_ForecastEnabled","name":"User_Role_ForecastManager_ForecastEnabled","type":"Text","label":"User_Role_ForecastManager_ForecastEnabled"},{"fullyQualifiedName":"Account_CreatedDate","name":"Account_CreatedDate","type":"Date","label":"Account_CreatedDate","format":"yyyy-MM-dd'T'HH:mm:ss.SSS'Z'"},{"fullyQualifiedName":"Account_User_Role_RolePath","name":"Account_User_Role_RolePath","type":"Text","label":"Account_User_Role_RolePath"},{"fullyQualifiedName":"Account_User_Role_ParentRole_ForecastManager_UniqueUserName","name":"Account_User_Role_ParentRole_ForecastManager_UniqueUserName","type":"Text","label":"Account_User_Role_ParentRole_ForecastManager_UniqueUserName"},{"fullyQualifiedName":"Account_User_Role_ForecastManager_Name","name":"Account_User_Role_ForecastManager_Name","type":"Text","label":"Account_User_Role_ForecastManager_Name"},{"fullyQualifiedName":"Account_User_Role_RoleNamesPath","name":"Account_User_Role_RoleNamesPath","type":"Text","label":"Account_User_Role_RoleNamesPath"},{"fullyQualifiedName":"Account_User_Role_ParentRole_ForecastManager_Name","name":"Account_User_Role_ParentRole_ForecastManager_Name","type":"Text","label":"Account_User_Role_ParentRole_ForecastManager_Name"},{"fullyQualifiedName":"User_Name","name":"User_Name","type":"Text","label":"User_Name"},{"fullyQualifiedName":"Account_User_Role_ForecastManager_ForecastEnabled","name":"Account_User_Role_ForecastManager_ForecastEnabled","type":"Text","label":"Account_User_Role_ForecastManager_ForecastEnabled"},{"fullyQualifiedName":"Account_User_Name","name":"Account_User_Name","type":"Text","label":"Account_User_Name"},{"fullyQualifiedName":"User_UniqueUserName","name":"User_UniqueUserName","type":"Text","label":"User_UniqueUserName"},{"fullyQualifiedName":"User_Role_ParentRoleId","name":"User_Role_ParentRoleId","type":"Text","label":"User_Role_ParentRoleId"},{"fullyQualifiedName":"Account_User_Role_ParentRole_Name","name":"Account_User_Role_ParentRole_Name","type":"Text","label":"Account_User_Role_ParentRole_Name"},{"fullyQualifiedName":"LeadSource","name":"LeadSource","type":"Text","label":"LeadSource"},{"fullyQualifiedName":"Account_BillingCountry","name":"Account_BillingCountry","type":"Text","label":"Account_BillingCountry"},{"fullyQualifiedName":"User_Role_ParentRole_ForecastManager_Name","name":"User_Role_ParentRole_ForecastManager_Name","type":"Text","label":"User_Role_ParentRole_ForecastManager_Name"},{"fullyQualifiedName":"User_Role_Roles","name":"User_Role_Roles","type":"Text","label":"User_Role_Roles"},{"fullyQualifiedName":"CreatedDate","name":"CreatedDate","type":"Date","label":"CreatedDate","format":"yyyy-MM-dd'T'HH:mm:ss.SSS'Z'"},{"fullyQualifiedName":"Account_OwnerId","name":"Account_OwnerId","type":"Text","label":"Account_OwnerId"},{"fullyQualifiedName":"User_ForecastEnabled","name":"User_ForecastEnabled","type":"Text","label":"User_ForecastEnabled"},{"fullyQualifiedName":"Account_User_Role_Roles","name":"Account_User_Role_Roles","type":"Text","label":"Account_User_Role_Roles"},{"fullyQualifiedName":"Id","name":"Id","type":"Text","label":"Id"},{"fullyQualifiedName":"ForecastCategoryName","name":"ForecastCategoryName","type":"Text","label":"ForecastCategoryName"},{"fullyQualifiedName":"Account_User_Role_RoleNames","name":"Account_User_Role_RoleNames","type":"Text","label":"Account_User_Role_RoleNames"},{"fullyQualifiedName":"Account_LastActivityDate","name":"Account_LastActivityDate","type":"Date","label":"Account_LastActivityDate","format":"yyyy-MM-dd"},{"fullyQualifiedName":"User_Role_RoleNamesPath","name":"User_Role_RoleNamesPath","type":"Text","label":"User_Role_RoleNamesPath"},{"fullyQualifiedName":"User_SmallPhotoUrl","name":"User_SmallPhotoUrl","type":"Text","label":"User_SmallPhotoUrl"},{"fullyQualifiedName":"User_UserRoleId","name":"User_UserRoleId","type":"Text","label":"User_UserRoleId"},{"fullyQualifiedName":"User_Role_ParentRole_ForecastManager_UniqueUserName","name":"User_Role_ParentRole_ForecastManager_UniqueUserName","type":"Text","label":"User_Role_ParentRole_ForecastManager_UniqueUserName"},{"fullyQualifiedName":"IsClosed","name":"IsClosed","type":"Text","label":"IsClosed"},{"fullyQualifiedName":"Account_User_Username","name":"Account_User_Username","type":"Text","label":"Account_User_Username"},{"fullyQualifiedName":"Account_User_Role_DeveloperName","name":"Account_User_Role_DeveloperName","type":"Text","label":"Account_User_Role_DeveloperName"},{"fullyQualifiedName":"User_Role_ParentRole_DeveloperName","name":"User_Role_ParentRole_DeveloperName","type":"Text","label":"User_Role_ParentRole_DeveloperName"},{"fullyQualifiedName":"Account_User_UniqueUserName","name":"Account_User_UniqueUserName","type":"Text","label":"Account_User_UniqueUserName"},{"fullyQualifiedName":"Account_Industry","name":"Account_Industry","type":"Text","label":"Account_Industry"},{"fullyQualifiedName":"Account_User_Role_ForecastManager_UniqueUserName","name":"Account_User_Role_ForecastManager_UniqueUserName","type":"Text","label":"Account_User_Role_ForecastManager_UniqueUserName"},{"fullyQualifiedName":"User_Role_DeveloperName","name":"User_Role_DeveloperName","type":"Text","label":"User_Role_DeveloperName"},{"fullyQualifiedName":"User_IsActive","name":"User_IsActive","type":"Text","label":"User_IsActive"},{"fullyQualifiedName":"OwnerId","name":"OwnerId","type":"Text","label":"OwnerId"},{"fullyQualifiedName":"IsWon","name":"IsWon","type":"Text","label":"IsWon"},{"fullyQualifiedName":"Account_User_Role_Name","name":"Account_User_Role_Name","type":"Text","label":"Account_User_Role_Name"},{"fullyQualifiedName":"User_Role_ParentRole_Name","name":"User_Role_ParentRole_Name","type":"Text","label":"User_Role_ParentRole_Name"},{"fullyQualifiedName":"Account_User_Role_ParentRoleId","name":"Account_User_Role_ParentRoleId","type":"Text","label":"Account_User_Role_ParentRoleId"},{"fullyQualifiedName":"Account_AccountSource","name":"Account_AccountSource","type":"Text","label":"Account_AccountSource"},{"fullyQualifiedName":"StageName","name":"StageName","type":"Text","label":"StageName"},{"fullyQualifiedName":"Account_BillingState","name":"Account_BillingState","type":"Text","label":"Account_BillingState"},{"fullyQualifiedName":"User_Role_RoleNames","name":"User_Role_RoleNames","type":"Text","label":"User_Role_RoleNames"},{"fullyQualifiedName":"User_AccountId","name":"User_AccountId","type":"Text","label":"User_AccountId"},{"fullyQualifiedName":"Type","name":"Type","type":"Text","label":"Type"},{"fullyQualifiedName":"Account_User_Role_ParentRole_DeveloperName","name":"Account_User_Role_ParentRole_DeveloperName","type":"Text","label":"Account_User_Role_ParentRole_DeveloperName"},{"fullyQualifiedName":"LastActivityDate","name":"LastActivityDate","type":"Date","label":"LastActivityDate","format":"yyyy-MM-dd"},{"fullyQualifiedName":"Account_Name","name":"Account_Name","type":"Text","label":"Account_Name"},{"fullyQualifiedName":"Account_User_ForecastEnabled","name":"Account_User_ForecastEnabled","type":"Text","label":"Account_User_ForecastEnabled"},{"fullyQualifiedName":"User_Role_RolePath","name":"User_Role_RolePath","type":"Text","label":"User_Role_RolePath"},{"fullyQualifiedName":"Account_AnnualRevenue","name":"Account_AnnualRevenue","type":"Numeric","label":"Account_AnnualRevenue","precision":18,"defaultValue":"null","scale":0,"format":"0","currencySymbol":"$"},{"fullyQualifiedName":"Account_NumberOfEmployees","name":"Account_NumberOfEmployees","type":"Numeric","label":"Account_NumberOfEmployees","precision":18,"defaultValue":"null","scale":0,"format":"0"},{"fullyQualifiedName":"Amount","name":"Amount","type":"Numeric","label":"Amount","precision":18,"defaultValue":"null","scale":0,"format":"0","currencySymbol":"$"},{"fullyQualifiedName":"Probability","name":"Probability","type":"Numeric","label":"Probability","precision":18,"defaultValue":"null","scale":0,"format":"0"}]}]}